LICENSE
MANIFEST.in
setup.py
pyweixin2/Weixin.py
pyweixin2/WeixinException.py
pyweixin2/__init__.py
pyweixin2.egg-info/PKG-INFO
pyweixin2.egg-info/SOURCES.txt
pyweixin2.egg-info/dependency_links.txt
pyweixin2.egg-info/not-zip-safe
pyweixin2.egg-info/requires.txt
pyweixin2.egg-info/top_level.txt
tests/__init__.py
tests/test.py