Metadata-Version: 1.1
Name: pyweixin2
Version: 0.2
Summary: Weixin Software Development Kit(Python)
Home-page: https://github.com/lockmind/weixin-python-sdk
Author: Freedom(WangChao)
Author-email: wangchao0126@gmail.com
License: MIT
Download-URL: https://github.com/lockmind/weixin-python-sdk/archive/master.zip
Keywords: weixin,sdk
Platform: any
